tumoroscope/__init__.py
tumoroscope/mock_data.py
tumoroscope/model.py
tumoroscope/tumoroscope_data.py
tumoroscope/utilities.py
tumoroscope_pymc-0.1.0.dist-info/LICENSE
tumoroscope_pymc-0.1.0.dist-info/WHEEL
tumoroscope_pymc-0.1.0.dist-info/METADATA
tumoroscope_pymc-0.1.0.dist-info/RECORD
