Metadata-Version: 2.1
Name: tumoroscope-pymc
Version: 0.1.0
Summary: 'Tumoroscope' model built with PyMC.
Keywords: pymc,bayesian,tumoroscope,model,spatial-transcriptomics
Author-email: Joshua Cook <joshuacook0023@gmail.com>
Requires-Python: >=3.9
Classifier: License :: OSI Approved :: GNU General Public License v3 or later (GPLv3+)
Classifier: Intended Audience :: Science/Research
Classifier: Topic :: Scientific/Engineering :: Bio-Informatics
Classifier: Typing :: Typed
Requires-Dist: numpy >= 1.23.0
Requires-Dist: pymc >= 4.0.0
Project-URL: Home, https://github.com/jhrcook/tumoroscope-pymc
